setup.py
ternion_python/__init__.py
ternion_python/ternion_commander.py
ternion_python/ternion_commander_api.py
ternion_python/ternion_gui.py
ternion_python/ternion_gui_api.py
ternion_python/ternion_monitor.py
ternion_python/ternion_monitor_api.py
ternion_python.egg-info/PKG-INFO
ternion_python.egg-info/SOURCES.txt
ternion_python.egg-info/dependency_links.txt
ternion_python.egg-info/requires.txt
ternion_python.egg-info/top_level.txt
ternion_python/core/__init__.py
ternion_python/core/ternion_board_utils.py
ternion_python/core/ternion_board_utils_api.py
ternion_python/core/ternion_link.py
ternion_python/core/ternion_link_api.py
ternion_python/core/ternion_logs.py
ternion_python/core/ternion_port_utils.py
ternion_python/core/ternion_port_utils_api.py